README.md
setup.py
cdisutils/__init__.py
cdisutils/dbgap.py
cdisutils/dictionary.py
cdisutils/errors.py
cdisutils/excel.py
cdisutils/log.py
cdisutils/net.py
cdisutils/psqlgraph_utils.py
cdisutils/settings.py
cdisutils/storage.py
cdisutils/tungsten.py
cdisutils.egg-info/PKG-INFO
cdisutils.egg-info/SOURCES.txt
cdisutils.egg-info/dependency_links.txt
cdisutils.egg-info/requires.txt
cdisutils.egg-info/top_level.txt
test/test_boto_utils.py
test/test_psqlgraph_utils.py
test/test_storage.py