Metadata-Version: 1.0
Name: cdisutils
Version: 1.2.2
Summary: Miscellaneous utilities useful for interaction with CDIS systems.
Home-page: UNKNOWN
Author: UNKNOWN
Author-email: UNKNOWN
License: Apache
Platform: UNKNOWN
